{
  "today": [
    {
      "startDate": "2026-05-04T19:00Z",
      "home": "Sevilla",
      "away": "Real Sociedad",
      "homeLogo": "https://a.espncdn.com/i/teamlogos/soccer/500/243.png",
      "awayLogo": "https://a.espncdn.com/i/teamlogos/soccer/500/89.png",
      "competition": "",
      "broadcast": "ESPN Deportes"
    },
    {
      "startDate": "2026-05-04T14:00Z",
      "home": "Chelsea",
      "away": "Nottingham Forest",
      "homeLogo": "https://a.espncdn.com/i/teamlogos/soccer/500/363.png",
      "awayLogo": "https://a.espncdn.com/i/teamlogos/soccer/500/393.png",
      "competition": "",
      "broadcast": "USA Net"
    },
    {
      "startDate": "2026-05-04T19:00Z",
      "home": "Everton",
      "away": "Manchester City",
      "homeLogo": "https://a.espncdn.com/i/teamlogos/soccer/500/368.png",
      "awayLogo": "https://a.espncdn.com/i/teamlogos/soccer/500/382.png",
      "competition": "",
      "broadcast": "USA Net"
    }
  ],
  "future": [
    {
      "startDate": "2026-05-09T19:00Z",
      "home": "Coritiba",
      "away": "Internacional",
      "homeLogo": "https://a.espncdn.com/i/teamlogos/soccer/500/3456.png",
      "awayLogo": "https://a.espncdn.com/i/teamlogos/soccer/500/1936.png",
      "competition": "",
      "broadcast": ""
    },
    {
      "startDate": "2026-05-09T21:00Z",
      "home": "Fluminense",
      "away": "Vitória",
      "homeLogo": "https://a.espncdn.com/i/teamlogos/soccer/500/3445.png",
      "awayLogo": "https://a.espncdn.com/i/teamlogos/soccer/500/3457.png",
      "competition": "",
      "broadcast": ""
    },
    {
      "startDate": "2026-05-10T00:00Z",
      "home": "Bahia",
      "away": "Cruzeiro",
      "homeLogo": "https://a.espncdn.com/i/teamlogos/soccer/500/9967.png",
      "awayLogo": "https://a.espncdn.com/i/teamlogos/soccer/500/2022.png",
      "competition": "",
      "broadcast": ""
    },
    {
      "startDate": "2026-05-10T19:00Z",
      "home": "Atlético-MG",
      "away": "Botafogo",
      "homeLogo": "https://a.espncdn.com/i/teamlogos/soccer/500/7632.png",
      "awayLogo": "https://a.espncdn.com/i/teamlogos/soccer/500/6086.png",
      "competition": "",
      "broadcast": ""
    },
    {
      "startDate": "2026-05-10T19:00Z",
      "home": "Remo",
      "away": "Palmeiras",
      "homeLogo": "https://a.espncdn.com/i/teamlogos/soccer/500/4936.png",
      "awayLogo": "https://a.espncdn.com/i/teamlogos/soccer/500/2029.png",
      "competition": "",
      "broadcast": ""
    },
    {
      "startDate": "2026-05-10T21:30Z",
      "home": "Corinthians",
      "away": "São Paulo",
      "homeLogo": "https://a.espncdn.com/i/teamlogos/soccer/500/874.png",
      "awayLogo": "https://a.espncdn.com/i/teamlogos/soccer/500/2026.png",
      "competition": "",
      "broadcast": ""
    },
    {
      "startDate": "2026-05-10T21:30Z",
      "home": "Mirassol",
      "away": "Chapecoense",
      "homeLogo": "https://a.espncdn.com/i/teamlogos/soccer/500/9169.png",
      "awayLogo": "https://a.espncdn.com/i/teamlogos/soccer/500/9318.png",
      "competition": "",
      "broadcast": ""
    },
    {
      "startDate": "2026-05-10T21:30Z",
      "home": "Santos",
      "away": "Red Bull Bragantino",
      "homeLogo": "https://a.espncdn.com/i/teamlogos/soccer/500/2674.png",
      "awayLogo": "https://a.espncdn.com/i/teamlogos/soccer/500/6079.png",
      "competition": "",
      "broadcast": ""
    },
    {
      "startDate": "2026-05-10T22:30Z",
      "home": "Grêmio",
      "away": "Flamengo",
      "homeLogo": "https://a.espncdn.com/i/teamlogos/soccer/500/6273.png",
      "awayLogo": "https://a.espncdn.com/i/teamlogos/soccer/500/819.png",
      "competition": "",
      "broadcast": ""
    },
    {
      "startDate": "2026-05-10T23:30Z",
      "home": "Vasco da Gama",
      "away": "Athletico-PR",
      "homeLogo": "https://a.espncdn.com/i/teamlogos/soccer/500/3454.png",
      "awayLogo": "https://a.espncdn.com/i/teamlogos/soccer/500/3458.png",
      "competition": "",
      "broadcast": ""
    },
    {
      "startDate": "2026-05-05T22:00Z",
      "home": "Sporting Cristal",
      "away": "Palmeiras",
      "homeLogo": "https://a.espncdn.com/i/teamlogos/soccer/500/2673.png",
      "awayLogo": "https://a.espncdn.com/i/teamlogos/soccer/500/2029.png",
      "competition": "",
      "broadcast": ""
    },
    {
      "startDate": "2026-05-06T00:00Z",
      "home": "Barcelona SC",
      "away": "Boca Juniors",
      "homeLogo": "https://a.espncdn.com/i/teamlogos/soccer/500/2686.png",
      "awayLogo": "https://a.espncdn.com/i/teamlogos/soccer/500/5.png",
      "competition": "",
      "broadcast": ""
    },
    {
      "startDate": "2026-05-07T00:30Z",
      "home": "Independiente Rivadavia",
      "away": "Fluminense",
      "homeLogo": "https://a.espncdn.com/i/teamlogos/soccer/500/9744.png",
      "awayLogo": "https://a.espncdn.com/i/teamlogos/soccer/500/3445.png",
      "competition": "",
      "broadcast": ""
    },
    {
      "startDate": "2026-05-07T00:30Z",
      "home": "Independiente Santa Fe",
      "away": "Corinthians",
      "homeLogo": "https://a.espncdn.com/i/teamlogos/soccer/500/5488.png",
      "awayLogo": "https://a.espncdn.com/i/teamlogos/soccer/500/874.png",
      "competition": "",
      "broadcast": ""
    },
    {
      "startDate": "2026-05-07T02:00Z",
      "home": "Deportes Tolima",
      "away": "Nacional",
      "homeLogo": "https://a.espncdn.com/i/teamlogos/soccer/500/5489.png",
      "awayLogo": "https://a.espncdn.com/i/teamlogos/soccer/500/2684.png",
      "competition": "",
      "broadcast": ""
    },
    {
      "startDate": "2026-05-07T02:00Z",
      "home": "Universidad Católica",
      "away": "Cruzeiro",
      "homeLogo": "https://a.espncdn.com/i/teamlogos/soccer/500/885.png",
      "awayLogo": "https://a.espncdn.com/i/teamlogos/soccer/500/2022.png",
      "competition": "",
      "broadcast": ""
    },
    {
      "startDate": "2026-05-07T22:00Z",
      "home": "Mirassol",
      "away": "Liga de Quito",
      "homeLogo": "https://a.espncdn.com/i/teamlogos/soccer/500/9169.png",
      "awayLogo": "https://a.espncdn.com/i/teamlogos/soccer/500/4816.png",
      "competition": "",
      "broadcast": ""
    },
    {
      "startDate": "2026-05-07T22:00Z",
      "home": "Platense",
      "away": "Peñarol",
      "homeLogo": "https://a.espncdn.com/i/teamlogos/soccer/500/7764.png",
      "awayLogo": "https://a.espncdn.com/i/teamlogos/soccer/500/2683.png",
      "competition": "",
      "broadcast": ""
    },
    {
      "startDate": "2026-05-08T00:30Z",
      "home": "Independiente Medellín",
      "away": "Flamengo",
      "homeLogo": "https://a.espncdn.com/i/teamlogos/soccer/500/2690.png",
      "awayLogo": "https://a.espncdn.com/i/teamlogos/soccer/500/819.png",
      "competition": "",
      "broadcast": ""
    },
    {
      "startDate": "2026-05-05T22:00Z",
      "home": "Deportivo Riestra",
      "away": "Grêmio",
      "homeLogo": "https://a.espncdn.com/i/teamlogos/soccer/500/17702.png",
      "awayLogo": "https://a.espncdn.com/i/teamlogos/soccer/500/6273.png",
      "competition": "",
      "broadcast": ""
    },
    {
      "startDate": "2026-05-05T22:00Z",
      "home": "Juventud",
      "away": "Atlético-MG",
      "homeLogo": "https://a.espncdn.com/i/teamlogos/soccer/500/8416.png",
      "awayLogo": "https://a.espncdn.com/i/teamlogos/soccer/500/7632.png",
      "competition": "",
      "broadcast": ""
    },
    {
      "startDate": "2026-05-06T00:30Z",
      "home": "Deportivo Recoleta",
      "away": "Santos",
      "homeLogo": "https://a.espncdn.com/i/teamlogos/soccer/500/22517.png",
      "awayLogo": "https://a.espncdn.com/i/teamlogos/soccer/500/2674.png",
      "competition": "",
      "broadcast": ""
    },
    {
      "startDate": "2026-05-06T22:00Z",
      "home": "Audax Italiano",
      "away": "Vasco da Gama",
      "homeLogo": "https://a.espncdn.com/i/teamlogos/soccer/500/4138.png",
      "awayLogo": "https://a.espncdn.com/i/teamlogos/soccer/500/3454.png",
      "competition": "",
      "broadcast": ""
    },
    {
      "startDate": "2026-05-07T00:30Z",
      "home": "Botafogo",
      "away": "Racing Club",
      "homeLogo": "https://a.espncdn.com/i/teamlogos/soccer/500/6086.png",
      "awayLogo": "https://a.espncdn.com/i/teamlogos/soccer/500/15.png",
      "competition": "",
      "broadcast": ""
    },
    {
      "startDate": "2026-05-07T22:00Z",
      "home": "O'Higgins",
      "away": "São Paulo",
      "homeLogo": "https://a.espncdn.com/i/teamlogos/soccer/500/6072.png",
      "awayLogo": "https://a.espncdn.com/i/teamlogos/soccer/500/2026.png",
      "competition": "",
      "broadcast": ""
    },
    {
      "startDate": "2026-05-08T00:30Z",
      "home": "Blooming",
      "away": "Red Bull Bragantino",
      "homeLogo": "https://a.espncdn.com/i/teamlogos/soccer/500/6047.png",
      "awayLogo": "https://a.espncdn.com/i/teamlogos/soccer/500/6079.png",
      "competition": "",
      "broadcast": ""
    },
    {
      "startDate": "2026-05-08T00:30Z",
      "home": "Carabobo",
      "away": "River Plate",
      "homeLogo": "https://a.espncdn.com/i/teamlogos/soccer/500/6037.png",
      "awayLogo": "https://a.espncdn.com/i/teamlogos/soccer/500/16.png",
      "competition": "",
      "broadcast": ""
    },
    {
      "startDate": "2026-05-07T00:30Z",
      "home": "Vitória",
      "away": "Ceará",
      "homeLogo": "https://a.espncdn.com/i/teamlogos/soccer/500/3457.png",
      "awayLogo": "https://a.espncdn.com/i/teamlogos/soccer/500/9969.png",
      "competition": "",
      "broadcast": ""
    },
    {
      "startDate": "2026-05-09T14:15Z",
      "home": "Sevilla",
      "away": "Espanyol",
      "homeLogo": "https://a.espncdn.com/i/teamlogos/soccer/500/243.png",
      "awayLogo": "https://a.espncdn.com/i/teamlogos/soccer/500/88.png",
      "competition": "",
      "broadcast": "ESPN Deportes"
    },
    {
      "startDate": "2026-05-09T16:30Z",
      "home": "Atlético Madrid",
      "away": "Celta Vigo",
      "homeLogo": "https://a.espncdn.com/i/teamlogos/soccer/500/1068.png",
      "awayLogo": "https://a.espncdn.com/i/teamlogos/soccer/500/85.png",
      "competition": "",
      "broadcast": "ESPN Deportes"
    },
    {
      "startDate": "2026-05-10T14:15Z",
      "home": "Athletic Club",
      "away": "Valencia",
      "homeLogo": "https://a.espncdn.com/i/teamlogos/soccer/500/93.png",
      "awayLogo": "https://a.espncdn.com/i/teamlogos/soccer/500/94.png",
      "competition": "",
      "broadcast": "ESPN Deportes"
    },
    {
      "startDate": "2026-05-10T19:00Z",
      "home": "Barcelona",
      "away": "Real Madrid",
      "homeLogo": "https://a.espncdn.com/i/teamlogos/soccer/500/83.png",
      "awayLogo": "https://a.espncdn.com/i/teamlogos/soccer/500/86.png",
      "competition": "",
      "broadcast": "ESPN"
    },
    {
      "startDate": "2026-05-09T11:30Z",
      "home": "Liverpool",
      "away": "Chelsea",
      "homeLogo": "https://a.espncdn.com/i/teamlogos/soccer/500/364.png",
      "awayLogo": "https://a.espncdn.com/i/teamlogos/soccer/500/363.png",
      "competition": "",
      "broadcast": ""
    },
    {
      "startDate": "2026-05-09T14:00Z",
      "home": "Sunderland",
      "away": "Manchester United",
      "homeLogo": "https://a.espncdn.com/i/teamlogos/soccer/500/366.png",
      "awayLogo": "https://a.espncdn.com/i/teamlogos/soccer/500/360.png",
      "competition": "",
      "broadcast": ""
    },
    {
      "startDate": "2026-05-09T16:30Z",
      "home": "Manchester City",
      "away": "Brentford",
      "homeLogo": "https://a.espncdn.com/i/teamlogos/soccer/500/382.png",
      "awayLogo": "https://a.espncdn.com/i/teamlogos/soccer/500/337.png",
      "competition": "",
      "broadcast": ""
    },
    {
      "startDate": "2026-05-10T15:30Z",
      "home": "West Ham United",
      "away": "Arsenal",
      "homeLogo": "https://a.espncdn.com/i/teamlogos/soccer/500/371.png",
      "awayLogo": "https://a.espncdn.com/i/teamlogos/soccer/500/359.png",
      "competition": "",
      "broadcast": ""
    },
    {
      "startDate": "2026-05-09T18:45Z",
      "home": "Lecce",
      "away": "Juventus",
      "homeLogo": "https://a.espncdn.com/i/teamlogos/soccer/500/113.png",
      "awayLogo": "https://a.espncdn.com/i/teamlogos/soccer/500/111.png",
      "competition": "",
      "broadcast": "Paramount+"
    },
    {
      "startDate": "2026-05-10T18:45Z",
      "home": "AC Milan",
      "away": "Atalanta",
      "homeLogo": "https://a.espncdn.com/i/teamlogos/soccer/500/103.png",
      "awayLogo": "https://a.espncdn.com/i/teamlogos/soccer/500/105.png",
      "competition": "",
      "broadcast": "Paramount+"
    },
    {
      "startDate": "2026-05-11T18:45Z",
      "home": "Napoli",
      "away": "Bologna",
      "homeLogo": "https://a.espncdn.com/i/teamlogos/soccer/500/114.png",
      "awayLogo": "https://a.espncdn.com/i/teamlogos/soccer/500/107.png",
      "competition": "",
      "broadcast": "Paramount+"
    },
    {
      "startDate": "2026-05-08T18:30Z",
      "home": "Borussia Dortmund",
      "away": "Eintracht Frankfurt",
      "homeLogo": "https://a.espncdn.com/i/teamlogos/soccer/500/124.png",
      "awayLogo": "https://a.espncdn.com/i/teamlogos/soccer/500/125.png",
      "competition": "",
      "broadcast": "ESPN+"
    },
    {
      "startDate": "2026-05-09T13:30Z",
      "home": "RB Leipzig",
      "away": "St. Pauli",
      "homeLogo": "https://a.espncdn.com/i/teamlogos/soccer/500/11420.png",
      "awayLogo": "https://a.espncdn.com/i/teamlogos/soccer/500/270.png",
      "competition": "",
      "broadcast": "ESPN+"
    },
    {
      "startDate": "2026-05-09T13:30Z",
      "home": "VfB Stuttgart",
      "away": "Bayer Leverkusen",
      "homeLogo": "https://a.espncdn.com/i/teamlogos/soccer/500/134.png",
      "awayLogo": "https://a.espncdn.com/i/teamlogos/soccer/500/131.png",
      "competition": "",
      "broadcast": "ESPN+"
    },
    {
      "startDate": "2026-05-10T19:00Z",
      "home": "Le Havre AC",
      "away": "Marseille",
      "homeLogo": "https://a.espncdn.com/i/teamlogos/soccer/500/3236.png",
      "awayLogo": "https://a.espncdn.com/i/teamlogos/soccer/500/176.png",
      "competition": "",
      "broadcast": ""
    },
    {
      "startDate": "2026-05-10T19:00Z",
      "home": "Paris Saint-Germain",
      "away": "Brest",
      "homeLogo": "https://a.espncdn.com/i/teamlogos/soccer/500/160.png",
      "awayLogo": "https://a.espncdn.com/i/teamlogos/soccer/500/6997.png",
      "competition": "",
      "broadcast": ""
    },
    {
      "startDate": "2026-05-10T19:00Z",
      "home": "Toulouse",
      "away": "Lyon",
      "homeLogo": "https://a.espncdn.com/i/teamlogos/soccer/500/179.png",
      "awayLogo": "https://a.espncdn.com/i/teamlogos/soccer/500/167.png",
      "competition": "",
      "broadcast": ""
    },
    {
      "startDate": "2026-05-05T19:00Z",
      "home": "Arsenal",
      "away": "Atlético Madrid",
      "homeLogo": "https://a.espncdn.com/i/teamlogos/soccer/500/359.png",
      "awayLogo": "https://a.espncdn.com/i/teamlogos/soccer/500/1068.png",
      "competition": "",
      "broadcast": "Paramount+"
    },
    {
      "startDate": "2026-05-06T19:00Z",
      "home": "Bayern Munich",
      "away": "Paris Saint-Germain",
      "homeLogo": "https://a.espncdn.com/i/teamlogos/soccer/500/132.png",
      "awayLogo": "https://a.espncdn.com/i/teamlogos/soccer/500/160.png",
      "competition": "",
      "broadcast": "Paramount+"
    }
  ]
}